[{"t":"14\/01\/2021","vib":1.885850668,"rpm":810.0603027,"bitola":8,"fmrb":"fm","vel":67},{"t":"15\/01\/2021","vib":2.260416746,"rpm":810.390625,"bitola":8,"fmrb":"fm","vel":67},{"t":"18\/01\/2021","vib":2.87543416,"rpm":1177.48877,"bitola":5.5,"fmrb":"fm","vel":97},{"t":"18\/01\/2021","vib":2.974826336,"rpm":1177.598877,"bitola":5.5,"fmrb":"fm","vel":97},{"t":"19\/01\/2021","vib":3.003472328,"rpm":1177.598877,"bitola":5.5,"fmrb":"fm","vel":97},{"t":"19\/01\/2021","vib":3.40668416,"rpm":1176.828125,"bitola":5.5,"fmrb":"fm","vel":97},{"t":"20\/01\/2021","vib":3.107638836,"rpm":1177.04834,"bitola":5.5,"fmrb":"fm","vel":97},{"t":"23\/01\/2021","vib":2.507378578,"rpm":1176.938232,"bitola":5.5,"fmrb":"fm","vel":97},{"t":"24\/01\/2021","vib":2.342447996,"rpm":1178.589844,"bitola":5.5,"fmrb":"fm","vel":97},{"t":"25\/01\/2021","vib":2.689670086,"rpm":1176.718018,"bitola":5.5,"fmrb":"fm","vel":97},{"t":"26\/01\/2021","vib":3.165798664,"rpm":1178.699951,"bitola":5.5,"fmrb":"fm","vel":97},{"t":"02\/01\/2021","rpm":3,"vib":4,"bitola":8,"fmrb":"rb","vel":63},{"t":"02\/02\/2021","rpm":756.7683105,"vib":3.142795086,"bitola":8,"fmrb":"rb","vel":63},{"t":"02\/02\/2021","rpm":756.7683105,"vib":3.494791746,"bitola":8,"fmrb":"rb","vel":63},{"t":"03\/02\/2021","rpm":756.7683105,"vib":2.753472328,"bitola":8,"fmrb":"rb","vel":63},{"t":"24\/02\/2021","rpm":1181.012207,"vib":2.585503578,"bitola":5.5,"fmrb":"fm","vel":97.1},{"t":"28\/02\/2021","rpm":1182.113281,"vib":3.754774332,"bitola":5.5,"fmrb":"fm","vel":97.1},{"t":"03\/03\/2021","rpm":1182.443604,"vib":3.923611164,"bitola":5.5,"fmrb":"fm","vel":97.1}]